aiida_yambo_wannier90/__init__.py
aiida_yambo_wannier90/calculations/__init__.py
aiida_yambo_wannier90/calculations/gw2wannier90.py
aiida_yambo_wannier90/calculations/functions/kmesh.py
aiida_yambo_wannier90/cli/__init__.py
aiida_yambo_wannier90/cli/data.py
aiida_yambo_wannier90/cli/plot.py
aiida_yambo_wannier90/cli/root.py
aiida_yambo_wannier90/common/__init__.py
aiida_yambo_wannier90/common/types.py
aiida_yambo_wannier90/parsers/gw2wannier90.py
aiida_yambo_wannier90/parsers/raw.py
aiida_yambo_wannier90/utils/__init__.py
aiida_yambo_wannier90/utils/builder.py
aiida_yambo_wannier90/utils/workflows.py
aiida_yambo_wannier90/workflows/__init__.py
aiida_yambo_wannier90/workflows/protocols/__init__.py
aiida_yambo_wannier90/workflows/protocols/yambo_wannier90.yaml
aiida_yambo_wannier90-0.1.0b0.dist-info/entry_points.txt
aiida_yambo_wannier90-0.1.0b0.dist-info/LICENSE
aiida_yambo_wannier90-0.1.0b0.dist-info/WHEEL
aiida_yambo_wannier90-0.1.0b0.dist-info/METADATA
aiida_yambo_wannier90-0.1.0b0.dist-info/RECORD
