Metadata-Version: 2.1
Name: aiida-yambo-wannier90
Version: 0.1.0b0
Summary: Plugin to combine Wannier90 interpolations with GW corrections computed by Yambo
Keywords: aiida,plugin
Author: The AiiDA Team
Requires-Python: >=3.7
Classifier: Programming Language :: Python
Classifier: Intended Audience :: Science/Research
Classifier: License :: OSI Approved :: MIT License
Classifier: Natural Language :: English
Classifier: Development Status :: 4 - Beta
Classifier: Framework :: AiiDA
Requires-Dist: aiida-core>=1.6.4,<3
Requires-Dist: voluptuous
Requires-Dist: aiida-yambo>=1.3.0
Requires-Dist: aiida-wannier90-workflows>=1.0.1
Requires-Dist: sphinx ; extra == "docs"
Requires-Dist: sphinxcontrib-contentui ; extra == "docs"
Requires-Dist: sphinxcontrib-details-directive ; extra == "docs"
Requires-Dist: furo ; extra == "docs"
Requires-Dist: markupsafe<2.1 ; extra == "docs"
Requires-Dist: pre-commit~=2.17 ; extra == "pre-commit"
Requires-Dist: pylint>=2.5.0,<2.9 ; extra == "pre-commit"
Requires-Dist: pgtest~=1.3.1 ; extra == "testing"
Requires-Dist: wheel~=0.31 ; extra == "testing"
Requires-Dist: coverage[toml] ; extra == "testing"
Requires-Dist: pytest~=6.0 ; extra == "testing"
Requires-Dist: pytest-cov ; extra == "testing"
Requires-Dist: pytest-regressions ; extra == "testing"
Project-URL: Source, https://github.com/aiidaplugins/aiida-yambo-wannier90
Provides-Extra: docs
Provides-Extra: pre-commit
Provides-Extra: testing
